aiandme/__init__.py
aiandme/firewall.py
aiandme/firewalloss.py
aiandme/model_providers/__init__.py
aiandme/model_providers/azureopenai.py
aiandme/model_providers/openai.py
aiandme/schemas/__init__.py
aiandme/schemas/agent.py
aiandme/schemas/firewall.py
aiandme/schemas/logs.py
aiandme-0.8.0.dist-info/licenses/LICENSE
aiandme-0.8.0.dist-info/METADATA
aiandme-0.8.0.dist-info/WHEEL
aiandme-0.8.0.dist-info/top_level.txt
aiandme-0.8.0.dist-info/RECORD
