Metadata-Version: 2.4
Name: aiandme
Version: 0.8.0
Summary: ai&me library for inetgration with the platform. Supports also the open source version of the firewall.
Author-email: Kostas Siabanis <hello@aiandme.io>, Demetris Gerogiannis <hello@aiandme.io>
Project-URL: Homepage, https://github.com/aiandme-io/firewall
Project-URL: Issues, https://github.com/aiandme-io/firewall/issues
Classifier: Programming Language :: Python :: 3
Classifier: License :: OSI Approved :: MIT License
Classifier: Operating System :: OS Independent
Requires-Python: >=3.10
License-File: LICENSE
Requires-Dist: openai>=1.55.3
Requires-Dist: pydantic>=2.9.2
Requires-Dist: pydantic_core>=2.23.4
Requires-Dist: requests>=2.32.3
Dynamic: license-file
